yt_dlp_transcript/__init__.py
yt_dlp_transcript-0.1.21.dist-info/licenses/LICENSE
yt_dlp_transcript-0.1.21.dist-info/METADATA
yt_dlp_transcript-0.1.21.dist-info/WHEEL
yt_dlp_transcript-0.1.21.dist-info/entry_points.txt
yt_dlp_transcript-0.1.21.dist-info/top_level.txt
yt_dlp_transcript-0.1.21.dist-info/RECORD
