Metadata-Version: 2.4
Name: yt-dlp-transcript
Version: 0.1.21
Summary: Handy yt-dlp wrapper to download Youtube videos transcripts
Author-email: Alexander Ryabov <alex.ryabov@gmail.com>
Project-URL: Homepage, https://github.com/haron/yt-dlp-transcript
Project-URL: Issues, https://github.com/haron/yt-dlp-transcript/issues
Classifier: Programming Language :: Python :: 3
Classifier: Operating System :: OS Independent
Requires-Python: >=3.11
License-File: LICENSE
Requires-Dist: yt-dlp==2025.05.22
Requires-Dist: ConfigArgParse>=1.7
Requires-Dist: srt>=3.5.3
Provides-Extra: test
Requires-Dist: pytest>=8.0.0; extra == "test"
Dynamic: license-file
